irv_datapkg/__init__.py
irv_datapkg/_version.py
irv_datapkg/zenodo.py
irv_datapkg-0.2.1.dist-info/METADATA
irv_datapkg-0.2.1.dist-info/WHEEL
irv_datapkg-0.2.1.dist-info/licenses/LICENSE
irv_datapkg-0.2.1.dist-info/RECORD
