Metadata-Version: 2.4
Name: irv-datapkg
Version: 0.2.1
Summary: Helper package for irv-datapkg workflow
Project-URL: Homepage, https://github.com/nismod/irv-datapkg
Project-URL: Bug Tracker, https://github.com/nismod/irv-datapkg/issues
Author-email: Tom Russell <tom.russell@ouce.ox.ac.uk>, Fred Thomas <fred.thomas@eci.ox.ac.uk>
License-Expression: MIT
License-File: LICENSE
Classifier: Operating System :: OS Independent
Classifier: Programming Language :: Python :: 3
Requires-Python: >=3.9
Requires-Dist: cdsapi
Requires-Dist: gdal>=3.3
Requires-Dist: geopandas>=0.13
Requires-Dist: pyproj
Requires-Dist: shapely>=2.0
Provides-Extra: dev
Requires-Dist: flake8; extra == 'dev'
Requires-Dist: hatch; extra == 'dev'
Requires-Dist: pytest; extra == 'dev'
Requires-Dist: pytest-cov; extra == 'dev'
